<?xml version="1.0" encoding="utf-8"?>
<!DOCTYPE nta PUBLIC '-//Uppaal Team//DTD Flat System 1.6//EN'
  'http://www.it.uu.se/research/group/darts/uppaal/flat-1_6.dtd'>
<nta>
  <declaration>clock cl; int temp; const int a = 2029; const int b = 2081; const int c = 2133; const int d = 2186; const int e = 2238; const int f = 2290; const int g = 2342;</declaration>
  <template>
    <name>TagModel</name>
    <declaration></declaration>
    <location id="id0" x="456" y="-28466">
      <name x="456" y="-28486">S0</name>
      <label kind="invariant" cl="456" y="-28446">cl &lt;= 0</label>
    </location>
    <location id="id1" x="639" y="-27945">
      <name x="639" y="-27965">S1</name>
      <label kind="invariant" cl="639" y="-27925">cl &lt;= 300</label>
    </location>
    <location id="id2" x="189" y="-17798">
      <name x="189" y="-17818">S277</name>
      <label kind="invariant" cl="189" y="-17778">cl &lt;= 42600</label>
    </location>
    <location id="id3" x="644" y="-27424">
      <name x="644" y="-27444">S2</name>
      <label kind="invariant" cl="644" y="-27404">cl &lt;= 600</label>
    </location>
    <location id="id4" x="650" y="-26903">
      <name x="650" y="-26923">S3</name>
      <label kind="invariant" cl="650" y="-26883">cl &lt;= 900</label>
    </location>
    <location id="id5" x="661" y="-26382">
      <name x="661" y="-26402">S4</name>
      <label kind="invariant" cl="661" y="-26362">cl &lt;= 25200</label>
    </location>
    <location id="id6" x="667" y="-25835">
      <name x="667" y="-25855">S85</name>
      <label kind="invariant" cl="667" y="-25815">cl &lt;= 25500</label>
    </location>
    <location id="id7" x="689" y="-25263">
      <name x="689" y="-25283">S86</name>
      <label kind="invariant" cl="689" y="-25243">cl &lt;= 25800</label>
    </location>
    <location id="id8" x="722" y="-24691">
      <name x="722" y="-24711">S87</name>
      <label kind="invariant" cl="722" y="-24671">cl &lt;= 26100</label>
    </location>
    <location id="id9" x="783" y="-24118">
      <name x="783" y="-24138">S88</name>
      <label kind="invariant" cl="783" y="-24098">cl &lt;= 26400</label>
    </location>
    <location id="id10" x="906" y="-23546">
      <name x="906" y="-23566">S89</name>
      <label kind="invariant" cl="906" y="-23526">cl &lt;= 28500</label>
    </location>
    <location id="id11" x="1006" y="-22974">
      <name x="1006" y="-22994">S90</name>
      <label kind="invariant" cl="1006" y="-22954">cl &lt;= 27900</label>
    </location>
    <location id="id12" x="650" y="-22974">
      <name x="650" y="-22994">S6</name>
      <label kind="invariant" cl="650" y="-22954">cl &lt;= 28800</label>
    </location>
    <location id="id13" x="817" y="-22402">
      <name x="817" y="-22422">S91</name>
      <label kind="invariant" cl="817" y="-22382">cl &lt;= 29100</label>
    </location>
    <location id="id14" x="1261" y="-22402">
      <name x="1261" y="-22422">S5</name>
      <label kind="invariant" cl="1261" y="-22382">cl &lt;= 28200</label>
    </location>
    <location id="id15" x="322" y="-16909">
      <name x="322" y="-16929">S368</name>
      <label kind="invariant" cl="322" y="-16889">cl &lt;= 29100</label>
    </location>
    <location id="id16" x="961" y="-21830">
      <name x="961" y="-21850">S98</name>
      <label kind="invariant" cl="961" y="-21810">cl &lt;= 83400</label>
    </location>
    <location id="id17" x="322" y="-16286">
      <name x="322" y="-16306">S374</name>
      <label kind="invariant" cl="322" y="-16266">cl &lt;= 32100</label>
    </location>
    <location id="id18" x="1828" y="-21257">
      <name x="1828" y="-21277">S99</name>
      <label kind="invariant" cl="1828" y="-21237">cl &lt;= 83700</label>
    </location>
    <location id="id19" x="2272" y="-20660">
      <name x="2272" y="-20680">S100</name>
      <label kind="invariant" cl="2272" y="-20640">cl &lt;= 84000</label>
    </location>
    <location id="id20" x="2778" y="-20036">
      <name x="2778" y="-20056">S101</name>
      <label kind="invariant" cl="2778" y="-20016">cl &lt;= 56400</label>
    </location>
    <location id="id21" x="2106" y="-20036">
      <name x="2106" y="-20056">S7</name>
      <label kind="invariant" cl="2106" y="-20016">cl &lt;= 54900</label>
    </location>
    <location id="id22" x="1917" y="-19147">
      <name x="1917" y="-19167">S102</name>
      <label kind="invariant" cl="1917" y="-19127">cl &lt;= 55200</label>
    </location>
    <location id="id23" x="1306" y="-18472">
      <name x="1306" y="-18492">S103</name>
      <label kind="invariant" cl="1306" y="-18452">cl &lt;= 55500</label>
    </location>
    <location id="id24" x="1433" y="-15662">
      <name x="1433" y="-15682">S8</name>
      <label kind="invariant" cl="1433" y="-15642">cl &lt;= 48900</label>
    </location>
    <location id="id25" x="1239" y="-15039">
      <name x="1239" y="-15059">S385</name>
      <label kind="invariant" cl="1239" y="-15019">cl &lt;= 49200</label>
    </location>
    <location id="id26" x="3367" y="-20660">
      <name x="3367" y="-20680">S110</name>
      <label kind="invariant" cl="3367" y="-20640">cl &lt;= 39000</label>
    </location>
    <location id="id27" x="2117" y="-18472">
      <name x="2117" y="-18492">S392</name>
      <label kind="invariant" cl="2117" y="-18452">cl &lt;= 47700</label>
    </location>
    <location id="id28" x="1711" y="-18472">
      <name x="1711" y="-18492">S10</name>
      <label kind="invariant" cl="1711" y="-18452">cl &lt;= 34800</label>
    </location>
    <location id="id29" x="1533" y="-17341">
      <name x="1533" y="-17361">S393</name>
      <label kind="invariant" cl="1533" y="-17321">cl &lt;= 35100</label>
    </location>
    <location id="id30" x="2083" y="-17798">
      <name x="2083" y="-17818">S9</name>
      <label kind="invariant" cl="2083" y="-17778">cl &lt;= 48000</label>
    </location>
    <location id="id31" x="2050" y="-16909">
      <name x="2050" y="-16929">S394</name>
      <label kind="invariant" cl="2050" y="-16889">cl &lt;= 48300</label>
    </location>
    <location id="id32" x="4772" y="-19604">
      <name x="4772" y="-19624">S131</name>
      <label kind="invariant" cl="4772" y="-19584">cl &lt;= 41100</label>
    </location>
    <location id="id33" x="3906" y="-5198">
      <name x="3906" y="-5218">S138</name>
      <label kind="invariant" cl="3906" y="-5178">cl &lt;= 81300</label>
    </location>
    <location id="id34" x="4017" y="-4574">
      <name x="4017" y="-4594">S139</name>
      <label kind="invariant" cl="4017" y="-4554">cl &lt;= 81600</label>
    </location>
    <location id="id35" x="4017" y="-3951">
      <name x="4017" y="-3971">S140</name>
      <label kind="invariant" cl="4017" y="-3931">cl &lt;= 81900</label>
    </location>
    <location id="id36" x="4039" y="-3327">
      <name x="4039" y="-3347">S141</name>
      <label kind="invariant" cl="4039" y="-3307">cl &lt;= 82200</label>
    </location>
    <location id="id37" x="4711" y="-2704">
      <name x="4711" y="-2724">S142</name>
      <label kind="invariant" cl="4711" y="-2684">cl &lt;= 82500</label>
    </location>
    <location id="id38" x="2061" y="-166">
      <name x="2061" y="-186">S150</name>
      <label kind="invariant" cl="2061" y="-146">cl &lt;= 80100</label>
    </location>
    <location id="id39" x="4656" y="-2058">
      <name x="4656" y="-2078">S143</name>
      <label kind="invariant" cl="4656" y="-2038">cl &lt;= 79500</label>
    </location>
    <location id="id40" x="4656" y="-1413">
      <name x="4656" y="-1433">S144</name>
      <label kind="invariant" cl="4656" y="-1393">cl &lt;= 79800</label>
    </location>
    <location id="id41" x="3983" y="-11304">
      <name x="3983" y="-11324">S221</name>
      <label kind="invariant" cl="3983" y="-11284">cl &lt;= 84300</label>
    </location>
    <location id="id42" x="4656" y="-789">
      <name x="4656" y="-809">S145</name>
      <label kind="invariant" cl="4656" y="-769">cl &lt;= 80100</label>
    </location>
    <location id="id43" x="4067" y="-2058">
      <name x="4067" y="-2078">S240</name>
      <label kind="invariant" cl="4067" y="-2038">cl &lt;= 86100</label>
    </location>
    <location id="id44" x="3533" y="-10706">
      <name x="3533" y="-10726">S11</name>
      <label kind="invariant" cl="3533" y="-10686">cl &lt;= 43800</label>
    </location>
    <location id="id45" x="3983" y="-10706">
      <name x="3983" y="-10726">S15</name>
      <label kind="invariant" cl="3983" y="-10686">cl &lt;= 79800</label>
    </location>
    <location id="id46" x="3983" y="-10108">
      <name x="3983" y="-10128">S241</name>
      <label kind="invariant" cl="3983" y="-10088">cl &lt;= 80100</label>
    </location>
    <location id="id47" x="3461" y="-10108">
      <name x="3461" y="-10128">S14</name>
      <label kind="invariant" cl="3461" y="-10088">cl &lt;= 44100</label>
    </location>
    <location id="id48" x="4039" y="-9459">
      <name x="4039" y="-9479">S242</name>
      <label kind="invariant" cl="4039" y="-9439">cl &lt;= 80400</label>
    </location>
    <location id="id49" x="3150" y="-9459">
      <name x="3150" y="-9479">S13</name>
      <label kind="invariant" cl="3150" y="-9439">cl &lt;= 44400</label>
    </location>
    <location id="id50" x="3150" y="-8785">
      <name x="3150" y="-8805">S243</name>
      <label kind="invariant" cl="3150" y="-8765">cl &lt;= 44700</label>
    </location>
    <location id="id51" x="4039" y="-8785">
      <name x="4039" y="-8805">S12</name>
      <label kind="invariant" cl="4039" y="-8765">cl &lt;= 80700</label>
    </location>
    <location id="id52" x="3061" y="-8110">
      <name x="3061" y="-8130">S426</name>
      <label kind="invariant" cl="3061" y="-8090">cl &lt;= 54600</label>
    </location>
    <location id="id53" x="1894" y="-16286">
      <name x="1894" y="-16306">S994</name>
      <label kind="invariant" cl="1894" y="-16266">cl &lt;= 48600</label>
    </location>
    <location id="id54" x="3100" y="-16909">
      <name x="3100" y="-16929">S186</name>
      <label kind="invariant" cl="3100" y="-16889">cl &lt;= 71400</label>
    </location>
    <location id="id55" x="3272" y="-16286">
      <name x="3272" y="-16306">S212</name>
      <label kind="invariant" cl="3272" y="-16266">cl &lt;= 71700</label>
    </location>
    <location id="id56" x="3761" y="-15662">
      <name x="3761" y="-15682">S215</name>
      <label kind="invariant" cl="3761" y="-15642">cl &lt;= 71100</label>
    </location>
    <location id="id57" x="4322" y="-15662">
      <name x="4322" y="-15682">S23</name>
      <label kind="invariant" cl="4322" y="-15642">cl &lt;= 72000</label>
    </location>
    <location id="id58" x="2739" y="-4574">
      <name x="2739" y="-4594">S168</name>
      <label kind="invariant" cl="2739" y="-4554">cl &lt;= 58800</label>
    </location>
    <location id="id59" x="4767" y="-15039">
      <name x="4767" y="-15059">S219</name>
      <label kind="invariant" cl="4767" y="-15019">cl &lt;= 72300</label>
    </location>
    <location id="id60" x="3228" y="-15039">
      <name x="3228" y="-15059">S19</name>
      <label kind="invariant" cl="3228" y="-15019">cl &lt;= 51300</label>
    </location>
    <location id="id61" x="3606" y="-15039">
      <name x="3606" y="-15059">S20</name>
      <label kind="invariant" cl="3606" y="-15019">cl &lt;= 59400</label>
    </location>
    <location id="id62" x="3983" y="-15039">
      <name x="3983" y="-15059">S21</name>
      <label kind="invariant" cl="3983" y="-15019">cl &lt;= 69000</label>
    </location>
    <location id="id63" x="4361" y="-15039">
      <name x="4361" y="-15059">S22</name>
      <label kind="invariant" cl="4361" y="-15019">cl &lt;= 71400</label>
    </location>
    <location id="id64" x="3072" y="-12359">
      <name x="3072" y="-12379">S518</name>
      <label kind="invariant" cl="3072" y="-12339">cl &lt;= 51600</label>
    </location>
    <location id="id65" x="4733" y="-14415">
      <name x="4733" y="-14435">S18</name>
      <label kind="invariant" cl="4733" y="-14395">cl &lt;= 72600</label>
    </location>
    <location id="id66" x="2839" y="-19147">
      <name x="2839" y="-19167">S1021</name>
      <label kind="invariant" cl="2839" y="-19127">cl &lt;= 56700</label>
    </location>
    <location id="id67" x="2883" y="-18472">
      <name x="2883" y="-18492">S1022</name>
      <label kind="invariant" cl="2883" y="-18452">cl &lt;= 57000</label>
    </location>
    <location id="id68" x="3083" y="-17798">
      <name x="3083" y="-17818">S1023</name>
      <label kind="invariant" cl="3083" y="-17778">cl &lt;= 57300</label>
    </location>
    <location id="id69" x="2967" y="-14415">
      <name x="2967" y="-14435">S220</name>
      <label kind="invariant" cl="2967" y="-14395">cl &lt;= 59700</label>
    </location>
    <location id="id70" x="4361" y="-14009">
      <name x="4361" y="-14029">S16</name>
      <label kind="invariant" cl="4361" y="-13989">cl &lt;= 71700</label>
    </location>
    <location id="id71" x="3983" y="-13197">
      <name x="3983" y="-13217">S17</name>
      <label kind="invariant" cl="3983" y="-13177">cl &lt;= 69300</label>
    </location>
    <location id="id72" x="4683" y="-13603">
      <name x="4683" y="-13623">S519</name>
      <label kind="invariant" cl="4683" y="-13583">cl &lt;= 78600</label>
    </location>
    <location id="id73" x="4039" y="-7653">
      <name x="4039" y="-7673">S244</name>
      <label kind="invariant" cl="4039" y="-7633">cl &lt;= 81000</label>
    </location>
    <location id="id74" x="3583" y="-9459">
      <name x="3583" y="-9479">S1085</name>
      <label kind="invariant" cl="3583" y="-9439">cl &lt;= 75900</label>
    </location>
    <location id="id75" x="3606" y="-8785">
      <name x="3606" y="-8805">S1086</name>
      <label kind="invariant" cl="3606" y="-8765">cl &lt;= 76200</label>
    </location>
    <location id="id76" x="3650" y="-8110">
      <name x="3650" y="-8130">S1087</name>
      <label kind="invariant" cl="3650" y="-8090">cl &lt;= 76500</label>
    </location>
    <location id="id77" x="3650" y="-7196">
      <name x="3650" y="-7216">S1088</name>
      <label kind="invariant" cl="3650" y="-7176">cl &lt;= 76800</label>
    </location>
    <location id="id78" x="3650" y="-6521">
      <name x="3650" y="-6541">S1089</name>
      <label kind="invariant" cl="3650" y="-6501">cl &lt;= 77100</label>
    </location>
    <location id="id79" x="3672" y="-5846">
      <name x="3672" y="-5866">S1090</name>
      <label kind="invariant" cl="3672" y="-5826">cl &lt;= 77400</label>
    </location>
    <location id="id80" x="4683" y="-12791">
      <name x="4683" y="-12811">S539</name>
      <label kind="invariant" cl="4683" y="-12771">cl &lt;= 78900</label>
    </location>
    <location id="id81" x="4683" y="-11927">
      <name x="4683" y="-11947">S540</name>
      <label kind="invariant" cl="4683" y="-11907">cl &lt;= 79200</label>
    </location>
    <init ref="id0"/>
    <transition>
      <source ref="id0"/>
      <target ref="id1"/>
      <label kind="guard">cl &gt;= 0 &amp;&amp; cl &lt;= 0</label>
      <label kind="assignment">temp = 2133, cl = 0</label>
    </transition>
    <transition>
      <source ref="id0"/>
      <target ref="id2"/>
      <label kind="guard">cl &gt;= 0 &amp;&amp; cl &lt;= 0</label>
      <label kind="assignment">temp = 2186, cl = 0</label>
    </transition>
    <transition>
      <source ref="id1"/>
      <target ref="id3"/>
      <label kind="guard">cl &gt;= 300 &amp;&amp; cl &lt;= 300</label>
      <label kind="assignment">temp = 2081, cl = 0</label>
    </transition>
    <transition>
      <source ref="id2"/>
      <target ref="id2"/>
      <label kind="guard">cl &gt;= 300 &amp;&amp; cl &lt;= 42300</label>
      <label kind="assignment">temp = 2186, cl = 0</label>
    </transition>
    <transition>
      <source ref="id2"/>
      <target ref="id2"/>
      <label kind="guard">cl &gt;= 600 &amp;&amp; cl &lt;= 41700</label>
      <label kind="assignment">temp = 2133, cl = 0</label>
    </transition>
    <transition>
      <source ref="id2"/>
      <target ref="id15"/>
      <label kind="guard">cl &gt;= 27300 &amp;&amp; cl &lt;= 27300</label>
      <label kind="assignment">temp = 2081, cl = 0</label>
    </transition>
    <transition>
      <source ref="id2"/>
      <target ref="id38"/>
      <label kind="guard">cl &gt;= 42300 &amp;&amp; cl &lt;= 42600</label>
      <label kind="assignment">temp = 2238, cl = 0</label>
    </transition>
    <transition>
      <source ref="id3"/>
      <target ref="id4"/>
      <label kind="guard">cl &gt;= 600 &amp;&amp; cl &lt;= 600</label>
      <label kind="assignment">temp = 2081, cl = 0</label>
    </transition>
    <transition>
      <source ref="id4"/>
      <target ref="id5"/>
      <label kind="guard">cl &gt;= 900 &amp;&amp; cl &lt;= 900</label>
      <label kind="assignment">temp = 2133, cl = 0</label>
    </transition>
    <transition>
      <source ref="id5"/>
      <target ref="id5"/>
      <label kind="guard">cl &gt;= 1200 &amp;&amp; cl &lt;= 24900</label>
      <label kind="assignment">temp = 2081, cl = 0</label>
    </transition>
    <transition>
      <source ref="id5"/>
      <target ref="id6"/>
      <label kind="guard">cl &gt;= 25200 &amp;&amp; cl &lt;= 25200</label>
      <label kind="assignment">temp = 2133, cl = 0</label>
    </transition>
    <transition>
      <source ref="id6"/>
      <target ref="id7"/>
      <label kind="guard">cl &gt;= 25500 &amp;&amp; cl &lt;= 25500</label>
      <label kind="assignment">temp = 2133, cl = 0</label>
    </transition>
    <transition>
      <source ref="id7"/>
      <target ref="id8"/>
      <label kind="guard">cl &gt;= 25800 &amp;&amp; cl &lt;= 25800</label>
      <label kind="assignment">temp = 2133, cl = 0</label>
    </transition>
    <transition>
      <source ref="id8"/>
      <target ref="id9"/>
      <label kind="guard">cl &gt;= 26100 &amp;&amp; cl &lt;= 26100</label>
      <label kind="assignment">temp = 2029, cl = 0</label>
    </transition>
    <transition>
      <source ref="id9"/>
      <target ref="id10"/>
      <label kind="guard">cl &gt;= 26400 &amp;&amp; cl &lt;= 26400</label>
      <label kind="assignment">temp = 2133, cl = 0</label>
    </transition>
    <transition>
      <source ref="id10"/>
      <target ref="id11"/>
      <label kind="guard">cl &gt;= 26700 &amp;&amp; cl &lt;= 27600</label>
      <label kind="assignment">temp = 2133, cl = 0</label>
    </transition>
    <transition>
      <source ref="id10"/>
      <target ref="id12"/>
      <label kind="guard">cl &gt;= 28500 &amp;&amp; cl &lt;= 28500</label>
      <label kind="assignment">temp = 2133, cl = 0</label>
    </transition>
    <transition>
      <source ref="id11"/>
      <target ref="id14"/>
      <label kind="guard">cl &gt;= 27000 &amp;&amp; cl &lt;= 27900</label>
      <label kind="assignment">temp = 2133, cl = 0</label>
    </transition>
    <transition>
      <source ref="id12"/>
      <target ref="id13"/>
      <label kind="guard">cl &gt;= 28800 &amp;&amp; cl &lt;= 28800</label>
      <label kind="assignment">temp = 2133, cl = 0</label>
    </transition>
    <transition>
      <source ref="id13"/>
      <target ref="id16"/>
      <label kind="guard">cl &gt;= 29100 &amp;&amp; cl &lt;= 29100</label>
      <label kind="assignment">temp = 2133, cl = 0</label>
    </transition>
    <transition>
      <source ref="id14"/>
      <target ref="id10"/>
      <label kind="guard">cl &gt;= 27300 &amp;&amp; cl &lt;= 28200</label>
      <label kind="assignment">temp = 2081, cl = 0</label>
    </transition>
    <transition>
      <source ref="id15"/>
      <target ref="id15"/>
      <label kind="guard">cl &gt;= 27600 &amp;&amp; cl &lt;= 28800</label>
      <label kind="assignment">temp = 2133, cl = 0</label>
    </transition>
    <transition>
      <source ref="id15"/>
      <target ref="id17"/>
      <label kind="guard">cl &gt;= 29100 &amp;&amp; cl &lt;= 29100</label>
      <label kind="assignment">temp = 2186, cl = 0</label>
    </transition>
    <transition>
      <source ref="id16"/>
      <target ref="id18"/>
      <label kind="guard">cl &gt;= 29400 &amp;&amp; cl &lt;= 83400</label>
      <label kind="assignment">temp = 2133, cl = 0</label>
    </transition>
    <transition>
      <source ref="id16"/>
      <target ref="id16"/>
      <label kind="guard">cl &gt;= 33000 &amp;&amp; cl &lt;= 83100</label>
      <label kind="assignment">temp = 2186, cl = 0</label>
    </transition>
    <transition>
      <source ref="id17"/>
      <target ref="id17"/>
      <label kind="guard">cl &gt;= 29400 &amp;&amp; cl &lt;= 31800</label>
      <label kind="assignment">temp = 2186, cl = 0</label>
    </transition>
    <transition>
      <source ref="id17"/>
      <target ref="id24"/>
      <label kind="guard">cl &gt;= 32100 &amp;&amp; cl &lt;= 32100</label>
      <label kind="assignment">temp = 2133, cl = 0</label>
    </transition>
    <transition>
      <source ref="id18"/>
      <target ref="id19"/>
      <label kind="guard">cl &gt;= 29700 &amp;&amp; cl &lt;= 83700</label>
      <label kind="assignment">temp = 2186, cl = 0</label>
    </transition>
    <transition>
      <source ref="id18"/>
      <target ref="id26"/>
      <label kind="guard">cl &gt;= 32700 &amp;&amp; cl &lt;= 32700</label>
      <label kind="assignment">temp = 2238, cl = 0</label>
    </transition>
    <transition>
      <source ref="id19"/>
      <target ref="id20"/>
      <label kind="guard">cl &gt;= 56100 &amp;&amp; cl &lt;= 56100</label>
      <label kind="assignment">temp = 2186, cl = 0</label>
    </transition>
    <transition>
      <source ref="id19"/>
      <target ref="id41"/>
      <label kind="guard">cl &gt;= 42900 &amp;&amp; cl &lt;= 84000</label>
      <label kind="assignment">temp = 2238, cl = 0</label>
    </transition>
    <transition>
      <source ref="id19"/>
      <target ref="id21"/>
      <label kind="guard">cl &gt;= 30000 &amp;&amp; cl &lt;= 54600</label>
      <label kind="assignment">temp = 2186, cl = 0</label>
    </transition>
    <transition>
      <source ref="id20"/>
      <target ref="id66"/>
      <label kind="guard">cl &gt;= 56400 &amp;&amp; cl &lt;= 56400</label>
      <label kind="assignment">temp = 2238, cl = 0</label>
    </transition>
    <transition>
      <source ref="id21"/>
      <target ref="id22"/>
      <label kind="guard">cl &gt;= 30300 &amp;&amp; cl &lt;= 54900</label>
      <label kind="assignment">temp = 2186, cl = 0</label>
    </transition>
    <transition>
      <source ref="id22"/>
      <target ref="id23"/>
      <label kind="guard">cl &gt;= 30600 &amp;&amp; cl &lt;= 55200</label>
      <label kind="assignment">temp = 2186, cl = 0</label>
    </transition>
    <transition>
      <source ref="id22"/>
      <target ref="id27"/>
      <label kind="guard">cl &gt;= 47400 &amp;&amp; cl &lt;= 47400</label>
      <label kind="assignment">temp = 2133, cl = 0</label>
    </transition>
    <transition>
      <source ref="id22"/>
      <target ref="id28"/>
      <label kind="guard">cl &gt;= 34500 &amp;&amp; cl &lt;= 34500</label>
      <label kind="assignment">temp = 2133, cl = 0</label>
    </transition>
    <transition>
      <source ref="id23"/>
      <target ref="id18"/>
      <label kind="guard">cl &gt;= 30900 &amp;&amp; cl &lt;= 55500</label>
      <label kind="assignment">temp = 2186, cl = 0</label>
    </transition>
    <transition>
      <source ref="id24"/>
      <target ref="id25"/>
      <label kind="guard">cl &gt;= 32400 &amp;&amp; cl &lt;= 48900</label>
      <label kind="assignment">temp = 2133, cl = 0</label>
    </transition>
    <transition>
      <source ref="id25"/>
      <target ref="id16"/>
      <label kind="guard">cl &gt;= 32700 &amp;&amp; cl &lt;= 49200</label>
      <label kind="assignment">temp = 2133, cl = 0</label>
    </transition>
    <transition>
      <source ref="id26"/>
      <target ref="id26"/>
      <label kind="guard">cl &gt;= 33000 &amp;&amp; cl &lt;= 38700</label>
      <label kind="assignment">temp = 2186, cl = 0</label>
    </transition>
    <transition>
      <source ref="id26"/>
      <target ref="id32"/>
      <label kind="guard">cl &gt;= 39000 &amp;&amp; cl &lt;= 39000</label>
      <label kind="assignment">temp = 2238, cl = 0</label>
    </transition>
    <transition>
      <source ref="id27"/>
      <target ref="id30"/>
      <label kind="guard">cl &gt;= 47700 &amp;&amp; cl &lt;= 47700</label>
      <label kind="assignment">temp = 2133, cl = 0</label>
    </transition>
    <transition>
      <source ref="id28"/>
      <target ref="id29"/>
      <label kind="guard">cl &gt;= 34800 &amp;&amp; cl &lt;= 34800</label>
      <label kind="assignment">temp = 2133, cl = 0</label>
    </transition>
    <transition>
      <source ref="id29"/>
      <target ref="id24"/>
      <label kind="guard">cl &gt;= 35100 &amp;&amp; cl &lt;= 35100</label>
      <label kind="assignment">temp = 2133, cl = 0</label>
    </transition>
    <transition>
      <source ref="id30"/>
      <target ref="id31"/>
      <label kind="guard">cl &gt;= 48000 &amp;&amp; cl &lt;= 48000</label>
      <label kind="assignment">temp = 2133, cl = 0</label>
    </transition>
    <transition>
      <source ref="id31"/>
      <target ref="id53"/>
      <label kind="guard">cl &gt;= 48300 &amp;&amp; cl &lt;= 48300</label>
      <label kind="assignment">temp = 2186, cl = 0</label>
    </transition>
    <transition>
      <source ref="id32"/>
      <target ref="id32"/>
      <label kind="guard">cl &gt;= 39300 &amp;&amp; cl &lt;= 40800</label>
      <label kind="assignment">temp = 2238, cl = 0</label>
    </transition>
    <transition>
      <source ref="id32"/>
      <target ref="id33"/>
      <label kind="guard">cl &gt;= 41100 &amp;&amp; cl &lt;= 41100</label>
      <label kind="assignment">temp = 2186, cl = 0</label>
    </transition>
    <transition>
      <source ref="id33"/>
      <target ref="id34"/>
      <label kind="guard">cl &gt;= 41400 &amp;&amp; cl &lt;= 81300</label>
      <label kind="assignment">temp = 2186, cl = 0</label>
    </transition>
    <transition>
      <source ref="id33"/>
      <target ref="id33"/>
      <label kind="guard">cl &gt;= 42900 &amp;&amp; cl &lt;= 77700</label>
      <label kind="assignment">temp = 2238, cl = 0</label>
    </transition>
    <transition>
      <source ref="id33"/>
      <target ref="id58"/>
      <label kind="guard">cl &gt;= 50100 &amp;&amp; cl &lt;= 50100</label>
      <label kind="assignment">temp = 2290, cl = 0</label>
    </transition>
    <transition>
      <source ref="id34"/>
      <target ref="id35"/>
      <label kind="guard">cl &gt;= 41700 &amp;&amp; cl &lt;= 81600</label>
      <label kind="assignment">temp = 2186, cl = 0</label>
    </transition>
    <transition>
      <source ref="id35"/>
      <target ref="id36"/>
      <label kind="guard">cl &gt;= 42000 &amp;&amp; cl &lt;= 81900</label>
      <label kind="assignment">temp = 2186, cl = 0</label>
    </transition>
    <transition>
      <source ref="id36"/>
      <target ref="id37"/>
      <label kind="guard">cl &gt;= 42300 &amp;&amp; cl &lt;= 82200</label>
      <label kind="assignment">temp = 2238, cl = 0</label>
    </transition>
    <transition>
      <source ref="id36"/>
      <target ref="id43"/>
      <label kind="guard">cl &gt;= 74400 &amp;&amp; cl &lt;= 74400</label>
      <label kind="assignment">temp = 2186, cl = 0</label>
    </transition>
    <transition>
      <source ref="id37"/>
      <target ref="id39"/>
      <label kind="guard">cl &gt;= 42600 &amp;&amp; cl &lt;= 79200</label>
      <label kind="assignment">temp = 2238, cl = 0</label>
    </transition>
    <transition>
      <source ref="id37"/>
      <target ref="id43"/>
      <label kind="guard">cl &gt;= 80400 &amp;&amp; cl &lt;= 82500</label>
      <label kind="assignment">temp = 2186, cl = 0</label>
    </transition>
    <transition>
      <source ref="id37"/>
      <target ref="id54"/>
      <label kind="guard">cl &gt;= 49200 &amp;&amp; cl &lt;= 49200</label>
      <label kind="assignment">temp = 2290, cl = 0</label>
    </transition>
    <transition>
      <source ref="id38"/>
      <target ref="id33"/>
      <label kind="guard">cl &gt;= 42600 &amp;&amp; cl &lt;= 45000</label>
      <label kind="assignment">temp = 2238, cl = 0</label>
    </transition>
    <transition>
      <source ref="id38"/>
      <target ref="id16"/>
      <label kind="guard">cl &gt;= 42900 &amp;&amp; cl &lt;= 80100</label>
      <label kind="assignment">temp = 2186, cl = 0</label>
    </transition>
    <transition>
      <source ref="id39"/>
      <target ref="id40"/>
      <label kind="guard">cl &gt;= 42900 &amp;&amp; cl &lt;= 79500</label>
      <label kind="assignment">temp = 2238, cl = 0</label>
    </transition>
    <transition>
      <source ref="id40"/>
      <target ref="id42"/>
      <label kind="guard">cl &gt;= 43200 &amp;&amp; cl &lt;= 79800</label>
      <label kind="assignment">temp = 2238, cl = 0</label>
    </transition>
    <transition>
      <source ref="id41"/>
      <target ref="id41"/>
      <label kind="guard">cl &gt;= 43200 &amp;&amp; cl &lt;= 74700</label>
      <label kind="assignment">temp = 2238, cl = 0</label>
    </transition>
    <transition>
      <source ref="id41"/>
      <target ref="id43"/>
      <label kind="guard">cl &gt;= 84300 &amp;&amp; cl &lt;= 84300</label>
      <label kind="assignment">temp = 2186, cl = 0</label>
    </transition>
    <transition>
      <source ref="id41"/>
      <target ref="id44"/>
      <label kind="guard">cl &gt;= 43500 &amp;&amp; cl &lt;= 43500</label>
      <label kind="assignment">temp = 2186, cl = 0</label>
    </transition>
    <transition>
      <source ref="id41"/>
      <target ref="id45"/>
      <label kind="guard">cl &gt;= 71700 &amp;&amp; cl &lt;= 79500</label>
      <label kind="assignment">temp = 2186, cl = 0</label>
    </transition>
    <transition>
      <source ref="id42"/>
      <target ref="id37"/>
      <label kind="guard">cl &gt;= 43500 &amp;&amp; cl &lt;= 80100</label>
      <label kind="assignment">temp = 2238, cl = 0</label>
    </transition>
    <transition>
      <source ref="id42"/>
      <target ref="id38"/>
      <label kind="guard">cl &gt;= 44700 &amp;&amp; cl &lt;= 79800</label>
      <label kind="assignment">temp = 2186, cl = 0</label>
    </transition>
    <transition>
      <source ref="id43"/>
      <target ref="id43"/>
      <label kind="guard">cl &gt;= 74700 &amp;&amp; cl &lt;= 86100</label>
      <label kind="assignment">temp = 2186, cl = 0</label>
    </transition>
    <transition>
      <source ref="id44"/>
      <target ref="id47"/>
      <label kind="guard">cl &gt;= 43800 &amp;&amp; cl &lt;= 43800</label>
      <label kind="assignment">temp = 2238, cl = 0</label>
    </transition>
    <transition>
      <source ref="id45"/>
      <target ref="id46"/>
      <label kind="guard">cl &gt;= 72000 &amp;&amp; cl &lt;= 79800</label>
      <label kind="assignment">temp = 2238, cl = 0</label>
    </transition>
    <transition>
      <source ref="id46"/>
      <target ref="id48"/>
      <label kind="guard">cl &gt;= 72300 &amp;&amp; cl &lt;= 80100</label>
      <label kind="assignment">temp = 2186, cl = 0</label>
    </transition>
    <transition>
      <source ref="id46"/>
      <target ref="id74"/>
      <label kind="guard">cl &gt;= 75600 &amp;&amp; cl &lt;= 75600</label>
      <label kind="assignment">temp = 2238, cl = 0</label>
    </transition>
    <transition>
      <source ref="id47"/>
      <target ref="id49"/>
      <label kind="guard">cl &gt;= 44100 &amp;&amp; cl &lt;= 44100</label>
      <label kind="assignment">temp = 2186, cl = 0</label>
    </transition>
    <transition>
      <source ref="id48"/>
      <target ref="id51"/>
      <label kind="guard">cl &gt;= 72600 &amp;&amp; cl &lt;= 80400</label>
      <label kind="assignment">temp = 2186, cl = 0</label>
    </transition>
    <transition>
      <source ref="id49"/>
      <target ref="id50"/>
      <label kind="guard">cl &gt;= 44400 &amp;&amp; cl &lt;= 44400</label>
      <label kind="assignment">temp = 2186, cl = 0</label>
    </transition>
    <transition>
      <source ref="id50"/>
      <target ref="id52"/>
      <label kind="guard">cl &gt;= 44700 &amp;&amp; cl &lt;= 44700</label>
      <label kind="assignment">temp = 2238, cl = 0</label>
    </transition>
    <transition>
      <source ref="id51"/>
      <target ref="id73"/>
      <label kind="guard">cl &gt;= 72900 &amp;&amp; cl &lt;= 80700</label>
      <label kind="assignment">temp = 2186, cl = 0</label>
    </transition>
    <transition>
      <source ref="id52"/>
      <target ref="id52"/>
      <label kind="guard">cl &gt;= 45000 &amp;&amp; cl &lt;= 54300</label>
      <label kind="assignment">temp = 2238, cl = 0</label>
    </transition>
    <transition>
      <source ref="id52"/>
      <target ref="id54"/>
      <label kind="guard">cl &gt;= 54600 &amp;&amp; cl &lt;= 54600</label>
      <label kind="assignment">temp = 2290, cl = 0</label>
    </transition>
    <transition>
      <source ref="id53"/>
      <target ref="id24"/>
      <label kind="guard">cl &gt;= 48600 &amp;&amp; cl &lt;= 48600</label>
      <label kind="assignment">temp = 2133, cl = 0</label>
    </transition>
    <transition>
      <source ref="id54"/>
      <target ref="id54"/>
      <label kind="guard">cl &gt;= 56400 &amp;&amp; cl &lt;= 66600</label>
      <label kind="assignment">temp = 2342, cl = 0</label>
    </transition>
    <transition>
      <source ref="id54"/>
      <target ref="id55"/>
      <label kind="guard">cl &gt;= 49500 &amp;&amp; cl &lt;= 71400</label>
      <label kind="assignment">temp = 2238, cl = 0</label>
    </transition>
    <transition>
      <source ref="id54"/>
      <target ref="id54"/>
      <label kind="guard">cl &gt;= 55800 &amp;&amp; cl &lt;= 70200</label>
      <label kind="assignment">temp = 2290, cl = 0</label>
    </transition>
    <transition>
      <source ref="id55"/>
      <target ref="id56"/>
      <label kind="guard">cl &gt;= 49800 &amp;&amp; cl &lt;= 70800</label>
      <label kind="assignment">temp = 2238, cl = 0</label>
    </transition>
    <transition>
      <source ref="id55"/>
      <target ref="id54"/>
      <label kind="guard">cl &gt;= 58800 &amp;&amp; cl &lt;= 58800</label>
      <label kind="assignment">temp = 2342, cl = 0</label>
    </transition>
    <transition>
      <source ref="id55"/>
      <target ref="id55"/>
      <label kind="guard">cl &gt;= 55200 &amp;&amp; cl &lt;= 68700</label>
      <label kind="assignment">temp = 2290, cl = 0</label>
    </transition>
    <transition>
      <source ref="id55"/>
      <target ref="id57"/>
      <label kind="guard">cl &gt;= 71700 &amp;&amp; cl &lt;= 71700</label>
      <label kind="assignment">temp = 2238, cl = 0</label>
    </transition>
    <transition>
      <source ref="id56"/>
      <target ref="id54"/>
      <label kind="guard">cl &gt;= 50100 &amp;&amp; cl &lt;= 71100</label>
      <label kind="assignment">temp = 2290, cl = 0</label>
    </transition>
    <transition>
      <source ref="id56"/>
      <target ref="id60"/>
      <label kind="guard">cl &gt;= 51000 &amp;&amp; cl &lt;= 51000</label>
      <label kind="assignment">temp = 2238, cl = 0</label>
    </transition>
    <transition>
      <source ref="id56"/>
      <target ref="id61"/>
      <label kind="guard">cl &gt;= 59100 &amp;&amp; cl &lt;= 59100</label>
      <label kind="assignment">temp = 2238, cl = 0</label>
    </transition>
    <transition>
      <source ref="id56"/>
      <target ref="id62"/>
      <label kind="guard">cl &gt;= 65400 &amp;&amp; cl &lt;= 68700</label>
      <label kind="assignment">temp = 2238, cl = 0</label>
    </transition>
    <transition>
      <source ref="id56"/>
      <target ref="id63"/>
      <label kind="guard">cl &gt;= 71100 &amp;&amp; cl &lt;= 71100</label>
      <label kind="assignment">temp = 2238, cl = 0</label>
    </transition>
    <transition>
      <source ref="id57"/>
      <target ref="id59"/>
      <label kind="guard">cl &gt;= 72000 &amp;&amp; cl &lt;= 72000</label>
      <label kind="assignment">temp = 2238, cl = 0</label>
    </transition>
    <transition>
      <source ref="id58"/>
      <target ref="id58"/>
      <label kind="guard">cl &gt;= 50400 &amp;&amp; cl &lt;= 58500</label>
      <label kind="assignment">temp = 2290, cl = 0</label>
    </transition>
    <transition>
      <source ref="id58"/>
      <target ref="id54"/>
      <label kind="guard">cl &gt;= 55500 &amp;&amp; cl &lt;= 58800</label>
      <label kind="assignment">temp = 2342, cl = 0</label>
    </transition>
    <transition>
      <source ref="id59"/>
      <target ref="id65"/>
      <label kind="guard">cl &gt;= 72300 &amp;&amp; cl &lt;= 72300</label>
      <label kind="assignment">temp = 2290, cl = 0</label>
    </transition>
    <transition>
      <source ref="id60"/>
      <target ref="id64"/>
      <label kind="guard">cl &gt;= 51300 &amp;&amp; cl &lt;= 51300</label>
      <label kind="assignment">temp = 2290, cl = 0</label>
    </transition>
    <transition>
      <source ref="id61"/>
      <target ref="id69"/>
      <label kind="guard">cl &gt;= 59400 &amp;&amp; cl &lt;= 59400</label>
      <label kind="assignment">temp = 2238, cl = 0</label>
    </transition>
    <transition>
      <source ref="id62"/>
      <target ref="id71"/>
      <label kind="guard">cl &gt;= 65700 &amp;&amp; cl &lt;= 69000</label>
      <label kind="assignment">temp = 2238, cl = 0</label>
    </transition>
    <transition>
      <source ref="id63"/>
      <target ref="id70"/>
      <label kind="guard">cl &gt;= 71400 &amp;&amp; cl &lt;= 71400</label>
      <label kind="assignment">temp = 2238, cl = 0</label>
    </transition>
    <transition>
      <source ref="id64"/>
      <target ref="id58"/>
      <label kind="guard">cl &gt;= 51600 &amp;&amp; cl &lt;= 51600</label>
      <label kind="assignment">temp = 2290, cl = 0</label>
    </transition>
    <transition>
      <source ref="id65"/>
      <target ref="id72"/>
      <label kind="guard">cl &gt;= 72600 &amp;&amp; cl &lt;= 72600</label>
      <label kind="assignment">temp = 2238, cl = 0</label>
    </transition>
    <transition>
      <source ref="id66"/>
      <target ref="id67"/>
      <label kind="guard">cl &gt;= 56700 &amp;&amp; cl &lt;= 56700</label>
      <label kind="assignment">temp = 2238, cl = 0</label>
    </transition>
    <transition>
      <source ref="id67"/>
      <target ref="id68"/>
      <label kind="guard">cl &gt;= 57000 &amp;&amp; cl &lt;= 57000</label>
      <label kind="assignment">temp = 2238, cl = 0</label>
    </transition>
    <transition>
      <source ref="id68"/>
      <target ref="id54"/>
      <label kind="guard">cl &gt;= 57300 &amp;&amp; cl &lt;= 57300</label>
      <label kind="assignment">temp = 2238, cl = 0</label>
    </transition>
    <transition>
      <source ref="id69"/>
      <target ref="id54"/>
      <label kind="guard">cl &gt;= 59700 &amp;&amp; cl &lt;= 59700</label>
      <label kind="assignment">temp = 2290, cl = 0</label>
    </transition>
    <transition>
      <source ref="id70"/>
      <target ref="id33"/>
      <label kind="guard">cl &gt;= 71700 &amp;&amp; cl &lt;= 71700</label>
      <label kind="assignment">temp = 2342, cl = 0</label>
    </transition>
    <transition>
      <source ref="id71"/>
      <target ref="id41"/>
      <label kind="guard">cl &gt;= 66000 &amp;&amp; cl &lt;= 69300</label>
      <label kind="assignment">temp = 2238, cl = 0</label>
    </transition>
    <transition>
      <source ref="id72"/>
      <target ref="id72"/>
      <label kind="guard">cl &gt;= 72900 &amp;&amp; cl &lt;= 78300</label>
      <label kind="assignment">temp = 2238, cl = 0</label>
    </transition>
    <transition>
      <source ref="id72"/>
      <target ref="id80"/>
      <label kind="guard">cl &gt;= 78600 &amp;&amp; cl &lt;= 78600</label>
      <label kind="assignment">temp = 2186, cl = 0</label>
    </transition>
    <transition>
      <source ref="id73"/>
      <target ref="id33"/>
      <label kind="guard">cl &gt;= 73200 &amp;&amp; cl &lt;= 81000</label>
      <label kind="assignment">temp = 2186, cl = 0</label>
    </transition>
    <transition>
      <source ref="id74"/>
      <target ref="id75"/>
      <label kind="guard">cl &gt;= 75900 &amp;&amp; cl &lt;= 75900</label>
      <label kind="assignment">temp = 2238, cl = 0</label>
    </transition>
    <transition>
      <source ref="id75"/>
      <target ref="id76"/>
      <label kind="guard">cl &gt;= 76200 &amp;&amp; cl &lt;= 76200</label>
      <label kind="assignment">temp = 2238, cl = 0</label>
    </transition>
    <transition>
      <source ref="id76"/>
      <target ref="id77"/>
      <label kind="guard">cl &gt;= 76500 &amp;&amp; cl &lt;= 76500</label>
      <label kind="assignment">temp = 2186, cl = 0</label>
    </transition>
    <transition>
      <source ref="id77"/>
      <target ref="id78"/>
      <label kind="guard">cl &gt;= 76800 &amp;&amp; cl &lt;= 76800</label>
      <label kind="assignment">temp = 2238, cl = 0</label>
    </transition>
    <transition>
      <source ref="id78"/>
      <target ref="id79"/>
      <label kind="guard">cl &gt;= 77100 &amp;&amp; cl &lt;= 77100</label>
      <label kind="assignment">temp = 2238, cl = 0</label>
    </transition>
    <transition>
      <source ref="id79"/>
      <target ref="id33"/>
      <label kind="guard">cl &gt;= 77400 &amp;&amp; cl &lt;= 77400</label>
      <label kind="assignment">temp = 2238, cl = 0</label>
    </transition>
    <transition>
      <source ref="id80"/>
      <target ref="id81"/>
      <label kind="guard">cl &gt;= 78900 &amp;&amp; cl &lt;= 78900</label>
      <label kind="assignment">temp = 2238, cl = 0</label>
    </transition>
    <transition>
      <source ref="id81"/>
      <target ref="id41"/>
      <label kind="guard">cl &gt;= 79200 &amp;&amp; cl &lt;= 79200</label>
      <label kind="assignment">temp = 2238, cl = 0</label>
    </transition>
  </template>
  <system>Process = TagModel(); system Process;</system>
  <queries>
    <query>
      <formula>simulate [&lt;=18000] { temp }</formula>
      <comment/>
    </query>
  </queries>
</nta>